{
  "info" : {
    "output" : "boot.img",
    "json" : "boot.json",
    "headerVersion" : 1,
    "headerSize" : 1648,
    "loadBase" : 0,
    "tagsOffset" : 2147483904,
    "board" : "",
    "pageSize" : 2048,
    "cmdline" : "console=ttyMSM0,115200,n8 androidboot.console=ttyMSM0 androidboot.hardware=qcom msm_rtb.filter=0x237 ehci-hcd.park=3 lpm_levels.sleep_disabled=1 androidboot.bootdevice=7824900.sdhci earlycon=msm_serial_dm,0x78af000 firmware_class.path=/vendor/firmware_mnt/image androidboot.usbconfigfs=true loop.max_part=7 buildvariant=user",
    "osVersion" : "9.0.0",
    "osPatchLevel" : "2020-02-00",
    "hash" : "66NgwVFkXmuCmKEklJ9K2fMgz5IAAAAAAAAAAAAAAAA=",
    "verify" : "VB2.0",
    "imageSize" : 67108864
  },
  "kernel" : {
    "file" : "build/unzip_boot/kernel",
    "position" : 2048,
    "size" : 14827900,
    "loadOffset" : 2147516416
  },
  "ramdisk" : {
    "file" : null,
    "position" : 14831616,
    "size" : 0,
    "loadOffset" : 2164260864
  },
  "secondBootloader" : null,
  "recoveryDtbo" : null,
  "dtb" : null
}